odoo/addons/website_event_sale_b2x_alt_price/README.rst
odoo/addons/website_event_sale_b2x_alt_price/__init__.py
odoo/addons/website_event_sale_b2x_alt_price/__manifest__.py
odoo/addons/website_event_sale_b2x_alt_price/i18n/website_event_sale_b2x_alt_price.pot
odoo/addons/website_event_sale_b2x_alt_price/models/__init__.py
odoo/addons/website_event_sale_b2x_alt_price/models/event_ticket.py
odoo/addons/website_event_sale_b2x_alt_price/readme/CONTRIBUTORS.rst
odoo/addons/website_event_sale_b2x_alt_price/readme/DESCRIPTION.rst
odoo/addons/website_event_sale_b2x_alt_price/readme/ROADMAP.rst
odoo/addons/website_event_sale_b2x_alt_price/readme/USAGE.rst
odoo/addons/website_event_sale_b2x_alt_price/static/description/icon.png
odoo/addons/website_event_sale_b2x_alt_price/static/description/index.html
odoo/addons/website_event_sale_b2x_alt_price/static/src/js/b2b.js
odoo/addons/website_event_sale_b2x_alt_price/static/src/js/b2c.js
odoo/addons/website_event_sale_b2x_alt_price/static/src/scss/website_event_sale_b2x_alt_price.scss
odoo/addons/website_event_sale_b2x_alt_price/templates/assets.xml
odoo/addons/website_event_sale_b2x_alt_price/templates/website_event_sale.xml
odoo/addons/website_event_sale_b2x_alt_price/tests/__init__.py
odoo/addons/website_event_sale_b2x_alt_price/tests/test_ui.py
odoo13_addon_website_event_sale_b2x_alt_price-13.0.1.0.1.dist-info/METADATA
odoo13_addon_website_event_sale_b2x_alt_price-13.0.1.0.1.dist-info/WHEEL
odoo13_addon_website_event_sale_b2x_alt_price-13.0.1.0.1.dist-info/top_level.txt
odoo13_addon_website_event_sale_b2x_alt_price-13.0.1.0.1.dist-info/RECORD
